adafruit_circuitpython_pycamera-1.5.3.dist-info/licenses/LICENSE
adafruit_pycamera/__init__.py
adafruit_pycamera/imageprocessing.py
adafruit_pycamera/ironbow.py
adafruit_pycamera/ov5640_autofocus.bin
adafruit_pycamera/ov5640_autofocus.bin.license
adafruit_circuitpython_pycamera-1.5.3.dist-info/METADATA
adafruit_circuitpython_pycamera-1.5.3.dist-info/WHEEL
adafruit_circuitpython_pycamera-1.5.3.dist-info/top_level.txt
adafruit_circuitpython_pycamera-1.5.3.dist-info/RECORD
