Metadata-Version: 2.4
Name: adafruit-circuitpython-pycamera
Version: 1.5.3
Summary: Library for the Adafruit PyCamera
Author-email: Adafruit Industries <circuitpython@adafruit.com>
License: MIT
Project-URL: Homepage, https://github.com/adafruit/Adafruit_CircuitPython_PyCamera
Keywords: adafruit,blinka,circuitpython,micropython,pycamera,camera,esp32s3,wifi,ov5640
Classifier: Intended Audience :: Developers
Classifier: Topic :: Software Development :: Libraries
Classifier: Topic :: Software Development :: Embedded Systems
Classifier: Topic :: System :: Hardware
Classifier: License :: OSI Approved :: MIT License
Classifier: Programming Language :: Python :: 3
License-File: LICENSE
Requires-Dist: Adafruit-Blinka
Requires-Dist: adafruit-circuitpython-busdevice
Requires-Dist: adafruit-circuitpython-aw9523
Requires-Dist: adafruit-circuitpython-lis3dh
Requires-Dist: adafruit-circuitpython-display-text
Requires-Dist: adafruit-circuitpython-neopixel
Requires-Dist: adafruit-circuitpython-debouncer
Provides-Extra: optional
Requires-Dist: adafruit-circuitpython-bitmapsaver; extra == "optional"
Requires-Dist: adafruit-circuitpython-imageload; extra == "optional"
Dynamic: license-file
